<?xml version="1.0" encoding="utf-8" ?>
<dwsync>
<file name="handgotb 2.ttf" server="ftp.ttminsight.cl//ttminsi1/ttminsight.cl/wwwroot/" local="127907038140000000" remote="129875164200000000" Dst="-1" />
<file name="handgotb.ttf" server="ftp.ttminsight.cl//ttminsi1/ttminsight.cl/wwwroot/" local="127907038140000000" remote="129875164200000000" Dst="-1" />
<file name="handgotl 2.ttf" server="ftp.ttminsight.cl//ttminsi1/ttminsight.cl/wwwroot/" local="127907038140000000" remote="129875164200000000" Dst="-1" />
<file name="handgotl.ttf" server="ftp.ttminsight.cl//ttminsi1/ttminsight.cl/wwwroot/" local="127907038140000000" remote="129875164200000000" Dst="-1" />
<file name="handgotb 2.ttf" server="www.ttminsight.cl/wwwroot/" local="132734754741474133" remote="132241487400000000" Dst="1" />
<file name="handgotb.ttf" server="www.ttminsight.cl/wwwroot/" local="132734754743513639" remote="132241487400000000" Dst="1" />
<file name="handgotl 2.ttf" server="www.ttminsight.cl/wwwroot/" local="132734754755357239" remote="132241487400000000" Dst="1" />
<file name="handgotl.ttf" server="www.ttminsight.cl/wwwroot/" local="132734754757395885" remote="132241487400000000" Dst="1" />
</dwsync>